{"stats":{"minecraft:dropped":{"minecraft:short_grass":2,"minecraft:lapis_lazuli":10,"minecraft:cooked_beef":6,"minecraft:glass_bottle":3,"minecraft:crossbow":1,"minecraft:warped_roots":3,"minecraft:cracked_stone_bricks":4,"minecraft:elytra":1,"minecraft:dirt":9,"minecraft:stone_button":1,"minecraft:bone_meal":1,"minecraft:sand":10,"minecraft:iron_pickaxe":2,"minecraft:dark_oak_planks":27,"minecraft:bone":23,"minecraft:stone_axe":4,"minecraft:cherry_boat":1,"minecraft:sugar_cane":3,"minecraft:iron_nugget":3,"minecraft:golden_chestplate":3,"minecraft:cobbled_deepslate":21,"minecraft:wheat":325,"minecraft:rotten_flesh":46,"minecraft:waxed_copper_block":4,"minecraft:salmon":19,"minecraft:heavy_weighted_pressure_plate":1,"minecraft:ladder":3,"minecraft:chiseled_tuff":1,"minecraft:wheat_seeds":31,"minecraft:golden_horse_armor":1,"minecraft:oak_fence":1,"minecraft:cobblestone":52,"minecraft:apple":12,"minecraft:waxed_weathered_copper_bulb":2,"minecraft:rabbit":1,"minecraft:diamond_helmet":3,"minecraft:dead_bush":1,"minecraft:red_dye":1,"minecraft:paper":3,"minecraft:iron_shovel":2,"minecraft:string":8,"minecraft:stone_sword":2,"minecraft:smooth_stone_slab":1,"minecraft:bowl":1,"minecraft:stone_shovel":2,"minecraft:white_carpet":340,"minecraft:iron_boots":1,"minecraft:name_tag":2,"minecraft:nether_bricks":1,"minecraft:shears":1,"minecraft:diamond_sword":2,"minecraft:potato":1084,"minecraft:hay_block":15,"minecraft:diamond_pickaxe":1,"minecraft:pink_shulker_box":1,"minecraft:spider_eye":6,"minecraft:barrel":1,"minecraft:bamboo":3,"minecraft:bow":3,"minecraft:waxed_exposed_copper_bulb":1,"minecraft:magma_block":1,"minecraft:acacia_boat":2,"minecraft:soul_sand":12,"minecraft:birch_planks":109,"minecraft:diamond_axe":1,"minecraft:oak_log":5,"minecraft:baked_potato":32,"minecraft:lantern":16,"minecraft:iron_horse_armor":2,"minecraft:dark_oak_log":1,"minecraft:glistering_melon_slice":1,"minecraft:birch_log":10,"minecraft:gold_ingot":4,"minecraft:gravel":1,"minecraft:purpur_block":1,"minecraft:blackstone":2,"minecraft:mangrove_roots":1,"minecraft:chiseled_tuff_bricks":2,"minecraft:diamond_shovel":1,"minecraft:carrot":191,"minecraft:poppy":3,"minecraft:gunpowder":194,"minecraft:bee_nest":4,"minecraft:chest":5,"minecraft:arrow":3,"minecraft:iron_bars":1,"minecraft:netherrack":778,"minecraft:firework_rocket":53,"minecraft:water_bucket":1,"minecraft:bread":17,"minecraft:waxed_oxidized_copper_door":4,"minecraft:golden_helmet":3,"minecraft:diamond_leggings":2,"minecraft:mangrove_propagule":3,"minecraft:lead":3,"minecraft:grass_block":1,"minecraft:stick":24,"minecraft:torch":30,"minecraft:waxed_copper_bulb":2,"minecraft:iron_door":3,"minecraft:iron_leggings":1,"minecraft:redstone":10,"minecraft:tuff_bricks":2,"minecraft:tuff":3,"minecraft:raw_iron":2,"minecraft:flint_and_steel":1,"minecraft:filled_map":2,"minecraft:diamond_chestplate":1,"minecraft:iron_chestplate":2,"minecraft:andesite":3,"minecraft:mossy_stone_bricks":2,"minecraft:oak_boat":2,"minecraft:oak_sapling":1,"minecraft:golden_sword":2,"minecraft:diamond_boots":3,"minecraft:slime_ball":6,"minecraft:waxed_oxidized_copper_grate":9,"minecraft:brick":28},"minecraft:picked_up":{"minecraft:flower_pot":13,"minecraft:anvil":4,"minecraft:lead":30,"minecraft:smithing_table":5,"minecraft:stone_slab":52,"minecraft:oak_stairs":6,"minecraft:enchanted_book":4,"minecraft:brewing_stand":10,"minecraft:golden_sword":2,"minecraft:amethyst_block":116,"minecraft:polished_blackstone_brick_stairs":4,"minecraft:music_disc_cat":3,"minecraft:string":83,"minecraft:dark_oak_trapdoor":49,"minecraft:soul_soil":67,"minecraft:cooked_salmon":6,"minecraft:shroomlight":1,"minecraft:diamond_leggings":1,"minecraft:gold_nugget":27,"minecraft:cobbled_deepslate":219,"minecraft:spruce_planks":47,"minecraft:trial_key":1,"minecraft:bubble_coral":2,"minecraft:melon_slice":48,"minecraft:dark_oak_door":22,"minecraft:golden_helmet":2,"minecraft:jukebox":1,"minecraft:composter":2,"minecraft:purpur_pillar":6,"minecraft:acacia_log":6,"minecraft:golden_axe":2,"minecraft:cherry_log":157,"minecraft:waxed_weathered_copper_bulb":3,"minecraft:golden_chestplate":3,"minecraft:cauldron":5,"minecraft:stone_sword":1,"minecraft:honey_bottle":3,"minecraft:horn_coral_fan":5,"minecraft:tropical_fish":10,"minecraft:carved_pumpkin":1,"minecraft:glowstone":154,"minecraft:end_rod":3,"minecraft:blaze_rod":11,"minecraft:iron_bars":1,"minecraft:birch_log":196,"minecraft:magma_block":1,"minecraft:feather":6,"minecraft:cooked_beef":8,"minecraft:iron_door":13,"minecraft:birch_slab":63,"minecraft:water_bucket":3,"minecraft:jungle_log":2,"minecraft:brown_wool":6,"minecraft:dark_oak_boat":3,"minecraft:smoker":2,"minecraft:flint":66,"minecraft:map":2,"minecraft:lantern":12,"minecraft:chipped_anvil":3,"minecraft:stonecutter":7,"minecraft:rabbit":1,"minecraft:diamond_helmet":1,"minecraft:glowstone_dust":28,"minecraft:moss_block":1,"minecraft:chiseled_polished_blackstone":1,"minecraft:warped_wart_block":4,"minecraft:loom":5,"minecraft:dark_oak_log":2888,"minecraft:barrel":4,"minecraft:polished_andesite":3,"minecraft:snout_armor_trim_smithing_template":1,"minecraft:lever":12,"minecraft:granite":586,"minecraft:golden_horse_armor":1,"minecraft:dark_oak_fence":49,"minecraft:diamond_pickaxe":1,"minecraft:mud":2,"minecraft:crafting_table":13,"minecraft:bee_nest":4,"minecraft:bubble_coral_fan":4,"minecraft:ominous_bottle":2,"minecraft:nether_wart":30,"minecraft:stripped_cherry_log":22,"minecraft:dragon_head":3,"minecraft:purpur_block":26,"minecraft:heavy_weighted_pressure_plate":2,"minecraft:wind_charge":3,"minecraft:cornflower":29,"minecraft:elytra":3,"minecraft:flint_and_steel":7,"minecraft:white_carpet":1039,"minecraft:glass_pane":8,"minecraft:cracked_stone_bricks":6,"minecraft:cartography_table":4,"minecraft:beef":79,"minecraft:chiseled_tuff":1,"minecraft:iron_nugget":59,"minecraft:poppy":38,"minecraft:spruce_slab":28,"minecraft:minecart":22,"minecraft:guster_pottery_sherd":1,"minecraft:birch_sapling":49,"minecraft:chest":63,"minecraft:piston":6,"minecraft:egg":5,"minecraft:copper_ore":1,"minecraft:sandstone":153,"minecraft:stone":378,"minecraft:oak_door":5,"minecraft:spruce_fence":4,"minecraft:fire_charge":22,"minecraft:carrot":873,"minecraft:redstone":374,"minecraft:music_disc_creator_music_box":1,"minecraft:tnt":1,"minecraft:beetroot_seeds":8,"minecraft:tube_coral_fan":2,"minecraft:shears":1,"minecraft:diamond_boots":2,"minecraft:hay_block":41,"minecraft:purpur_slab":4,"minecraft:gold_ingot":4,"minecraft:tuff_bricks":8,"minecraft:white_shulker_box":20,"minecraft:mutton":2,"minecraft:white_wool":78,"minecraft:bone_block":106,"minecraft:rail":136,"minecraft:stripped_oak_log":4,"minecraft:clock":1,"minecraft:filled_map":5,"minecraft:purpur_stairs":4,"minecraft:oak_log":114,"minecraft:ancient_debris":4,"minecraft:diorite_stairs":8,"minecraft:paper":31,"minecraft:white_banner":1,"minecraft:apple":63,"minecraft:stone_bricks":144,"minecraft:kelp":2,"minecraft:warped_stem":12,"minecraft:cherry_sign":2,"minecraft:dark_oak_stairs":279,"minecraft:dark_oak_slab":563,"minecraft:sweet_berries":392,"minecraft:red_wool":12,"minecraft:waxed_exposed_copper_bulb":2,"minecraft:gravel":441,"minecraft:spruce_sapling":15,"minecraft:spruce_log":221,"minecraft:crying_obsidian":21,"minecraft:polished_tuff":8,"minecraft:firework_rocket":37,"minecraft:slime_ball":33,"minecraft:short_grass":2,"minecraft:gray_wool":4,"minecraft:warped_roots":3,"minecraft:baked_potato":3,"minecraft:brown_banner":10,"minecraft:warped_nylium":2,"minecraft:stripped_dark_oak_log":94,"minecraft:mangrove_propagule":15,"minecraft:hopper":11,"minecraft:ender_pearl":7,"minecraft:shulker_shell":14,"minecraft:wheat":158,"minecraft:ender_chest":1,"minecraft:nether_brick_fence":8,"minecraft:potion":8,"minecraft:nether_brick":28,"minecraft:stone_brick_stairs":87,"minecraft:raw_copper":191,"minecraft:smooth_stone_slab":1,"minecraft:red_candle":7,"minecraft:sticky_piston":12,"minecraft:pink_shulker_box":7,"minecraft:sea_pickle":1,"minecraft:smooth_stone":32,"minecraft:bucket":2,"minecraft:red_dye":6,"minecraft:waxed_oxidized_copper_door":5,"minecraft:rose_bush":5,"minecraft:redstone_torch":14,"minecraft:cobblestone_slab":10,"minecraft:ender_eye":9,"minecraft:calcite":4,"minecraft:iron_boots":2,"minecraft:furnace":2,"minecraft:tipped_arrow":5,"minecraft:stick":307,"minecraft:polished_deepslate_stairs":20,"minecraft:oak_fence":1,"minecraft:torch":318,"minecraft:spruce_stairs":52,"minecraft:porkchop":11,"minecraft:pointed_dripstone":24,"minecraft:diorite":178,"minecraft:light_gray_banner":3,"minecraft:rotten_flesh":238,"minecraft:mangrove_roots":1,"minecraft:fire_coral_fan":5,"minecraft:obsidian":60,"minecraft:cod":1,"minecraft:cobblestone":3799,"minecraft:pink_petals":197,"minecraft:cherry_planks":53,"minecraft:magma_cream":5,"minecraft:repeater":1,"minecraft:andesite":467,"minecraft:potato":1865,"minecraft:tuff":10,"minecraft:stripped_birch_log":3,"minecraft:acacia_boat":3,"minecraft:lapis_lazuli":514,"minecraft:dirt":4098,"minecraft:glass":36,"minecraft:bone":94,"minecraft:bow":10,"minecraft:wheat_seeds":404,"minecraft:raw_gold":96,"minecraft:bell":5,"minecraft:grindstone":10,"minecraft:mossy_stone_bricks":2,"minecraft:fletching_table":8,"minecraft:bamboo":3501,"minecraft:powered_rail":27,"minecraft:oak_planks":38,"minecraft:stone_hoe":1,"minecraft:scrape_pottery_sherd":1,"minecraft:brain_coral":1,"minecraft:cooked_porkchop":5,"minecraft:waxed_oxidized_copper_bulb":1,"minecraft:poisonous_potato":11,"minecraft:sand":735,"minecraft:dead_bush":3,"minecraft:grass_block":8,"minecraft:spectral_arrow":108,"minecraft:shulker_box":1,"minecraft:mossy_cobblestone":8,"minecraft:diamond":140,"minecraft:slime_block":8,"minecraft:spruce_boat":2,"minecraft:soul_lantern":8,"minecraft:waxed_oxidized_copper_grate":9,"minecraft:cracked_polished_blackstone_bricks":23,"minecraft:crossbow":1,"minecraft:bone_meal":75,"minecraft:golden_apple":6,"minecraft:emerald":35,"minecraft:oak_sapling":31,"minecraft:netherrack":1544,"minecraft:bubble_coral_block":2,"minecraft:end_stone_bricks":3,"minecraft:cocoa_beans":6,"minecraft:charcoal":32,"minecraft:allium":1,"minecraft:splash_potion":2,"minecraft:chicken":3,"minecraft:ladder":52,"minecraft:chest_minecart":2,"minecraft:pink_wool":15,"minecraft:stone_brick_wall":1,"minecraft:gold_block":22,"minecraft:chain":10,"minecraft:brick":111,"minecraft:stone_stairs":2,"minecraft:moss_carpet":5,"minecraft:item_frame":3,"minecraft:birch_fence":5,"minecraft:blackstone":70,"minecraft:candle":42,"minecraft:oak_boat":34,"minecraft:observer":10,"minecraft:light_gray_wool":312,"minecraft:lectern":31,"minecraft:blue_shulker_box":16,"minecraft:sugar_cane":485,"minecraft:spruce_trapdoor":4,"minecraft:phantom_membrane":2,"minecraft:dark_oak_sapling":195,"minecraft:raw_iron":506,"minecraft:polished_blackstone_bricks":37,"minecraft:stone_button":1,"minecraft:iron_horse_armor":2,"minecraft:dark_oak_planks":1143,"minecraft:arrow":149,"minecraft:red_shulker_box":8,"minecraft:nether_bricks":38,"minecraft:saddle":8,"minecraft:glistering_melon_slice":9,"minecraft:dark_oak_button":21,"minecraft:basalt":2,"minecraft:glow_ink_sac":3,"minecraft:salmon":46,"minecraft:leather":83,"minecraft:birch_planks":144,"minecraft:waxed_copper_bulb":4,"minecraft:crimson_fungus":2,"minecraft:waxed_copper_block":20,"minecraft:cobblestone_wall":10,"minecraft:yellow_bed":2,"minecraft:gunpowder":85,"minecraft:cobblestone_stairs":29,"minecraft:coast_armor_trim_smithing_template":2,"minecraft:heart_of_the_sea":1,"minecraft:iron_ingot":51,"minecraft:soul_sand":54,"minecraft:book":24,"minecraft:scaffolding":405,"minecraft:warped_fungus":2,"minecraft:pumpkin":3,"minecraft:birch_boat":5,"minecraft:stone_brick_slab":154,"minecraft:quartz":102,"minecraft:dandelion":4,"minecraft:dripstone_block":12,"minecraft:amethyst_shard":28,"minecraft:soul_torch":20,"minecraft:blast_furnace":8,"minecraft:white_bed":11,"minecraft:dark_oak_fence_gate":2,"minecraft:spider_eye":15,"minecraft:pumpkin_seeds":8,"minecraft:campfire":2,"minecraft:cherry_sapling":79,"minecraft:acacia_slab":1,"minecraft:chiseled_tuff_bricks":3,"minecraft:coal":466},"minecraft:mined":{"minecraft:dark_oak_planks":348,"minecraft:dragon_wall_head":3,"minecraft:red_shulker_box":8,"minecraft:white_bed":8,"minecraft:fire_coral_wall_fan":6,"minecraft:cherry_log":142,"minecraft:jungle_leaves":5,"minecraft:obsidian":24,"minecraft:carved_pumpkin":1,"minecraft:potted_dead_bush":4,"minecraft:granite":306,"minecraft:chiseled_polished_blackstone":1,"minecraft:acacia_log":6,"minecraft:stone_brick_wall":1,"minecraft:horn_coral_fan":1,"minecraft:purpur_slab":2,"minecraft:bubble_coral_block":2,"minecraft:chiseled_tuff_bricks":4,"minecraft:hopper":7,"minecraft:tube_coral_block":1,"minecraft:crimson_fungus":1,"minecraft:nether_wart":20,"minecraft:spawner":1,"minecraft:polished_blackstone_bricks":30,"minecraft:tall_seagrass":19,"minecraft:magma_block":1,"minecraft:dark_oak_trapdoor":49,"minecraft:sticky_piston":5,"minecraft:cobbled_deepslate":6,"minecraft:fire":5,"minecraft:barrel":4,"minecraft:waxed_oxidized_copper_bulb":1,"minecraft:pumpkin":3,"minecraft:deepslate_lapis_ore":22,"minecraft:fletching_table":8,"minecraft:sculk_shrieker":1,"minecraft:water_cauldron":3,"minecraft:dirt_path":65,"minecraft:oak_stairs":1,"minecraft:small_amethyst_bud":1,"minecraft:white_shulker_box":20,"minecraft:smoker":2,"minecraft:soul_fire":6,"minecraft:amethyst_cluster":4,"minecraft:powder_snow":4,"minecraft:torch":72,"minecraft:blast_furnace":8,"minecraft:melon":8,"minecraft:glass":82,"minecraft:sugar_cane":269,"minecraft:potted_oak_sapling":1,"minecraft:amethyst_block":114,"minecraft:chain":10,"minecraft:waxed_copper_bulb":4,"minecraft:repeater":1,"minecraft:mud":1,"minecraft:light_gray_stained_glass":2,"minecraft:wheat":106,"minecraft:jukebox":1,"minecraft:waxed_copper_block":23,"minecraft:stone_brick_stairs":70,"minecraft:dark_oak_sapling":17,"minecraft:loom":5,"minecraft:blue_shulker_box":16,"minecraft:red_mushroom_block":1,"minecraft:stonecutter":7,"minecraft:deepslate":176,"minecraft:pink_shulker_box":7,"minecraft:mossy_cobblestone":8,"minecraft:cherry_sapling":1,"minecraft:dark_oak_log":2610,"minecraft:shulker_box":1,"minecraft:nether_bricks":33,"minecraft:dark_oak_fence":44,"minecraft:redstone_wire":2,"minecraft:cartography_table":3,"minecraft:horn_coral_wall_fan":6,"minecraft:pink_wool":2,"minecraft:horn_coral":1,"minecraft:redstone_ore":1,"minecraft:andesite":263,"minecraft:chiseled_tuff":1,"minecraft:potatoes":542,"minecraft:cobblestone_slab":4,"minecraft:vine":4,"minecraft:rail":100,"minecraft:warped_stem":12,"minecraft:brain_coral_wall_fan":1,"minecraft:bamboo_sapling":6,"minecraft:bamboo":415,"minecraft:waxed_weathered_copper_bulb":3,"minecraft:bone_block":108,"minecraft:white_wool":32,"minecraft:brain_coral":1,"minecraft:ender_chest":3,"minecraft:smithing_table":5,"minecraft:glass_pane":3,"minecraft:soul_sand":33,"minecraft:stone_brick_slab":85,"minecraft:observer":10,"minecraft:dandelion":3,"minecraft:cornflower":24,"minecraft:short_grass":267,"minecraft:warped_roots":1,"minecraft:campfire":2,"minecraft:purpur_pillar":6,"minecraft:copper_ore":19,"minecraft:tall_grass":6,"minecraft:deepslate_gold_ore":64,"minecraft:diorite":182,"minecraft:warped_wart_block":2,"minecraft:cobblestone_wall":11,"minecraft:white_carpet":3,"minecraft:spruce_log":246,"minecraft:birch_leaves":54,"minecraft:mangrove_leaves":1,"minecraft:dark_oak_button":3,"minecraft:gravel":163,"minecraft:dripstone_block":4,"minecraft:cobweb":40,"minecraft:stone_bricks":96,"minecraft:gold_ore":11,"minecraft:cherry_sign":2,"minecraft:chipped_anvil":3,"minecraft:infested_stone":4,"minecraft:fern":31,"minecraft:large_amethyst_bud":2,"minecraft:spruce_planks":16,"minecraft:farmland":5,"minecraft:sculk_vein":6,"minecraft:cobblestone_stairs":3,"minecraft:brewing_stand":10,"minecraft:spruce_trapdoor":2,"minecraft:budding_amethyst":10,"minecraft:grass_block":1715,"minecraft:cracked_polished_blackstone_bricks":16,"minecraft:bubble_coral_fan":1,"minecraft:soul_soil":39,"minecraft:composter":2,"minecraft:tuff_bricks":12,"minecraft:gilded_blackstone":1,"minecraft:smooth_stone":2,"minecraft:glowstone":166,"minecraft:iron_ore":198,"minecraft:polished_tuff":9,"minecraft:anvil":4,"minecraft:dark_oak_stairs":140,"minecraft:pointed_dripstone":2,"minecraft:iron_bars":1,"minecraft:end_stone_bricks":5,"minecraft:spruce_slab":17,"minecraft:deepslate_redstone_ore":45,"minecraft:blackstone":10,"minecraft:medium_amethyst_bud":4,"minecraft:purpur_stairs":3,"minecraft:calcite":4,"minecraft:poppy":40,"minecraft:chest":61,"minecraft:nether_quartz_ore":18,"minecraft:cobblestone":57,"minecraft:slime_block":8,"minecraft:waxed_chiseled_copper":1,"minecraft:grindstone":10,"minecraft:oak_planks":14,"minecraft:wall_torch":102,"minecraft:iron_door":9,"minecraft:cauldron":2,"minecraft:pink_petals":70,"minecraft:seagrass":23,"minecraft:stone_stairs":2,"minecraft:warped_nylium":8,"minecraft:red_candle":2,"minecraft:powered_rail":15,"minecraft:dark_oak_slab":252,"minecraft:dark_oak_door":11,"minecraft:birch_log":191,"minecraft:brown_wall_banner":9,"minecraft:light_gray_wool":1,"minecraft:purpur_block":17,"minecraft:oak_log":110,"minecraft:beetroots":1,"minecraft:waxed_oxidized_copper":1,"minecraft:waxed_oxidized_copper_door":5,"minecraft:sand":640,"minecraft:dirt":1339,"minecraft:netherrack":3907,"minecraft:ancient_debris":4,"minecraft:oak_leaves":79,"minecraft:nether_gold_ore":5,"minecraft:crying_obsidian":1,"minecraft:tuff":19,"minecraft:candle":15,"minecraft:dark_oak_leaves":71,"minecraft:deepslate_diamond_ore":84,"minecraft:oak_door":5,"minecraft:stripped_cherry_log":16,"minecraft:mangrove_roots":1,"minecraft:lever":1,"minecraft:ladder":4,"minecraft:tube_coral_wall_fan":5,"minecraft:decorated_pot":28,"minecraft:soul_campfire":4,"minecraft:spruce_leaves":14,"minecraft:acacia_slab":1,"minecraft:sandstone":95,"minecraft:mangrove_propagule":1,"minecraft:rooted_dirt":1,"minecraft:large_fern":2,"minecraft:hay_block":40,"minecraft:furnace":2,"minecraft:carrots":278,"minecraft:nether_sprouts":1,"minecraft:dark_oak_fence_gate":3,"minecraft:gold_block":22,"minecraft:bell":4,"minecraft:nether_brick_fence":7,"minecraft:bookshelf":4,"minecraft:shroomlight":1,"minecraft:deepslate_iron_ore":71,"minecraft:lantern":3,"minecraft:stripped_oak_log":4,"minecraft:packed_ice":2,"minecraft:stone":3600,"minecraft:podzol":114,"minecraft:waxed_exposed_copper_bulb":1,"minecraft:scaffolding":60,"minecraft:red_wool":12,"minecraft:magenta_stained_glass":1,"minecraft:stripped_dark_oak_log":92,"minecraft:basalt":5,"minecraft:oak_fence":1,"minecraft:crafting_table":12,"minecraft:light_gray_wall_banner":3,"minecraft:rose_bush":2,"minecraft:sculk_sensor":5,"minecraft:lectern":31,"minecraft:stone_slab":13,"minecraft:polished_blackstone_brick_stairs":3,"minecraft:sculk":9,"minecraft:spruce_stairs":29,"minecraft:birch_planks":2,"minecraft:bubble_coral":3,"minecraft:waxed_oxidized_copper_grate":9,"minecraft:redstone_torch":7,"minecraft:sweet_berry_bush":15,"minecraft:bee_nest":2,"minecraft:yellow_bed":2,"minecraft:coal_ore":229,"minecraft:cocoa":1,"minecraft:cherry_leaves":25,"minecraft:end_rod":3,"minecraft:bubble_coral_wall_fan":3,"minecraft:flower_pot":9,"minecraft:cracked_stone_bricks":4,"minecraft:polished_andesite":3,"minecraft:mossy_stone_bricks":1,"minecraft:birch_fence":1},"minecraft:broken":{"minecraft:iron_boots":1,"minecraft:iron_chestplate":1,"minecraft:iron_sword":1,"minecraft:stone_sword":1,"minecraft:iron_pickaxe":1,"minecraft:flint_and_steel":4},"minecraft:custom":{"minecraft:interact_with_crafting_table":369,"minecraft:open_barrel":87,"minecraft:bell_ring":221,"minecraft:leave_game":63,"minecraft:time_since_death":83886,"minecraft:play_time":2643842,"minecraft:deaths":63,"minecraft:jump":30033,"minecraft:enchant_item":19,"minecraft:interact_with_furnace":126,"minecraft:play_record":2,"minecraft:traded_with_villager":72,"minecraft:interact_with_cartography_table":2,"minecraft:sleep_in_bed":55,"minecraft:damage_dealt":89823,"minecraft:interact_with_smoker":3,"minecraft:inspect_dispenser":11,"minecraft:horse_one_cm":438,"minecraft:interact_with_smithing_table":7,"minecraft:interact_with_anvil":18,"minecraft:inspect_hopper":41,"minecraft:sneak_time":97548,"minecraft:interact_with_blast_furnace":6,"minecraft:total_world_time":2643842,"minecraft:interact_with_stonecutter":12,"minecraft:time_since_rest":6835,"minecraft:swim_one_cm":275351,"minecraft:fly_one_cm":7285479,"minecraft:open_chest":4057,"minecraft:fall_one_cm":872695,"minecraft:open_shulker_box":357,"minecraft:sprint_one_cm":4455215,"minecraft:drop":276,"minecraft:talked_to_villager":221,"minecraft:interact_with_brewingstand":5,"minecraft:walk_on_water_one_cm":155158,"minecraft:interact_with_loom":7,"minecraft:open_enderchest":131,"minecraft:crouch_one_cm":376754,"minecraft:mob_kills":589,"minecraft:climb_one_cm":128307,"minecraft:walk_one_cm":5184735,"minecraft:walk_under_water_one_cm":244774,"minecraft:boat_one_cm":587072,"minecraft:pot_flower":8,"minecraft:interact_with_grindstone":1,"minecraft:damage_taken":36375,"minecraft:aviate_one_cm":16941524},"minecraft:crafted":{"minecraft:purple_bed":1,"minecraft:pink_bed":2,"minecraft:chain":19,"minecraft:blaze_powder":4,"minecraft:birch_boat":1,"minecraft:slime_block":2,"minecraft:loom":1,"minecraft:diorite_stairs":8,"minecraft:lever":9,"minecraft:diamond_shovel":2,"minecraft:bookshelf":11,"minecraft:shulker_box":4,"minecraft:diamond_helmet":1,"minecraft:repeater":3,"minecraft:diamond_leggings":1,"minecraft:melon_seeds":12,"minecraft:iron_door":3,"minecraft:name_tag":2,"minecraft:white_shulker_box":1,"minecraft:flower_pot":10,"minecraft:glass_bottle":3,"minecraft:emerald":52,"minecraft:soul_campfire":2,"minecraft:diamond_axe":4,"minecraft:smithing_table":1,"minecraft:copper_ingot":45,"minecraft:sticky_piston":9,"minecraft:hay_block":4,"minecraft:campfire":13,"minecraft:polished_deepslate_slab":24,"minecraft:cartography_table":1,"minecraft:stone_brick_stairs":100,"minecraft:lectern":1,"minecraft:cherry_sign":3,"minecraft:stone_slab":78,"minecraft:iron_pickaxe":2,"minecraft:iron_block":13,"minecraft:gold_ingot":203,"minecraft:netherite_ingot":1,"minecraft:composter":3,"minecraft:golden_carrot":117,"minecraft:stone_shovel":3,"minecraft:jukebox":1,"minecraft:iron_nugget":675,"minecraft:polished_deepslate_stairs":20,"minecraft:soul_torch":28,"minecraft:blue_shulker_box":1,"minecraft:bone_meal":1215,"minecraft:spruce_fence":12,"minecraft:pink_dye":33,"minecraft:white_carpet":27,"minecraft:stone_stairs":20,"minecraft:lantern":50,"minecraft:dark_oak_fence":84,"minecraft:spruce_stairs":80,"minecraft:ladder":84,"minecraft:spruce_slab":60,"minecraft:red_shulker_box":1,"minecraft:stone_pickaxe":1,"minecraft:spruce_boat":1,"minecraft:dark_oak_planks":4996,"minecraft:allium":1,"minecraft:golden_helmet":3,"minecraft:wheat":207,"minecraft:netherite_pickaxe":1,"minecraft:enchanting_table":1,"minecraft:blue_bed":2,"minecraft:dark_oak_button":19,"minecraft:enchanted_book":2,"minecraft:soul_lantern":8,"minecraft:gunpowder":8,"minecraft:oak_stairs":8,"minecraft:iron_shovel":2,"minecraft:iron_leggings":2,"minecraft:white_bed":4,"minecraft:oak_planks":428,"minecraft:cobblestone_slab":42,"minecraft:barrel":11,"minecraft:dark_oak_boat":1,"minecraft:pink_shulker_box":1,"minecraft:cherry_boat":1,"minecraft:cobblestone_stairs":48,"minecraft:heavy_weighted_pressure_plate":1,"minecraft:dark_oak_door":24,"minecraft:hopper":18,"minecraft:stone_brick_slab":174,"minecraft:bow":2,"minecraft:iron_boots":2,"minecraft:chest":97,"minecraft:netherite_upgrade_smithing_template":8,"minecraft:rail":16,"minecraft:stone_hoe":2,"minecraft:ender_eye":3,"minecraft:stone_bricks":648,"minecraft:smoker":4,"minecraft:item_frame":6,"minecraft:cauldron":2,"minecraft:crafting_table":18,"minecraft:spruce_planks":866,"minecraft:iron_helmet":2,"minecraft:wooden_pickaxe":1,"minecraft:baked_potato":27,"minecraft:red_wool":19,"minecraft:birch_planks":500,"minecraft:pumpkin_seeds":4,"minecraft:sea_pickle":1,"minecraft:tnt":5,"minecraft:spruce_trapdoor":20,"minecraft:dark_oak_slab":678,"minecraft:book":45,"minecraft:iron_chestplate":2,"minecraft:paper":378,"minecraft:diamond_pickaxe":3,"minecraft:charcoal":29,"minecraft:pink_wool":32,"minecraft:purple_dye":6,"minecraft:stick":2262,"minecraft:iron_ingot":84,"minecraft:stone_sword":2,"minecraft:redstone_torch":12,"minecraft:dark_oak_fence_gate":5,"minecraft:shears":4,"minecraft:polished_andesite":1,"minecraft:cherry_planks":240,"minecraft:purple_wool":6,"minecraft:oak_door":3,"minecraft:stone_brick_wall":6,"minecraft:furnace":12,"minecraft:blast_furnace":1,"minecraft:piston":12,"minecraft:dark_oak_trapdoor":216,"minecraft:dark_oak_sign":15,"minecraft:glass_pane":32,"minecraft:flint_and_steel":12,"minecraft:scaffolding":234,"minecraft:polished_deepslate":64,"minecraft:iron_axe":1,"minecraft:cobblestone_wall":36,"minecraft:minecart":4,"minecraft:observer":1,"minecraft:red_dye":30,"minecraft:diamond_sword":3,"minecraft:dark_oak_stairs":300,"minecraft:powered_rail":6,"minecraft:iron_sword":1,"minecraft:bucket":3,"minecraft:stone_axe":5,"minecraft:air":0,"minecraft:acacia_boat":4,"minecraft:bread":27,"minecraft:blue_dye":18,"minecraft:oak_boat":5,"minecraft:white_wool":11,"minecraft:gold_nugget":963,"minecraft:white_dye":1,"minecraft:blue_wool":6,"minecraft:anvil":3,"minecraft:stonecutter":1,"minecraft:acacia_planks":24,"minecraft:torch":604,"minecraft:diamond_chestplate":1,"minecraft:firework_rocket":612},"minecraft:killed_by":{"minecraft:piglin_brute":1,"minecraft:bogged":1,"minecraft:zombie":3,"minecraft:ghast":1,"minecraft:wither_skeleton":1,"minecraft:creeper":4,"minecraft:cave_spider":1,"minecraft:player":2,"minecraft:spider":1,"minecraft:skeleton":3},"minecraft:used":{"minecraft:tuff_bricks":4,"minecraft:nether_brick_fence":2,"minecraft:ladder":64,"minecraft:spruce_slab":52,"minecraft:elytra":9,"minecraft:poppy":2,"minecraft:chest":97,"minecraft:white_shulker_box":20,"minecraft:stone":296,"minecraft:spruce_boat":1,"minecraft:red_wool":31,"minecraft:grass_block":7,"minecraft:birch_sapling":1,"minecraft:dark_oak_slab":715,"minecraft:dark_oak_button":17,"minecraft:pink_wool":10,"minecraft:stone_brick_stairs":93,"minecraft:dark_oak_boat":2,"minecraft:sweet_berries":278,"minecraft:furnace":6,"minecraft:oak_sapling":1,"minecraft:egg":1,"minecraft:potato":594,"minecraft:dragon_head":2,"minecraft:diorite":7,"minecraft:waxed_weathered_copper_bulb":1,"minecraft:stripped_birch_log":1,"minecraft:powered_rail":15,"minecraft:wooden_pickaxe":3,"minecraft:composter":5,"minecraft:glow_berries":8,"minecraft:dark_oak_trapdoor":261,"minecraft:sand":62,"minecraft:blast_furnace":9,"minecraft:pumpkin_seeds":10,"minecraft:crying_obsidian":12,"minecraft:lectern":32,"minecraft:cherry_sign":3,"minecraft:soul_lantern":8,"minecraft:chiseled_tuff_bricks":1,"minecraft:diamond_sword":1258,"minecraft:smithing_table":6,"minecraft:dark_oak_fence":98,"minecraft:birch_log":17,"minecraft:oak_boat":29,"minecraft:enchanting_table":1,"minecraft:stone_sword":131,"minecraft:carved_pumpkin":1,"minecraft:trial_key":1,"minecraft:netherrack":129,"minecraft:torch":591,"minecraft:brewing_stand":9,"minecraft:anvil":7,"minecraft:stone_stairs":20,"minecraft:red_shulker_box":8,"minecraft:chipped_anvil":3,"minecraft:iron_block":4,"minecraft:iron_axe":162,"minecraft:slime_block":10,"minecraft:barrel":11,"minecraft:melon_seeds":10,"minecraft:bamboo":161,"minecraft:diamond_chestplate":6,"minecraft:basalt":1,"minecraft:glowstone":104,"minecraft:cobbled_deepslate":57,"minecraft:cherry_log":68,"minecraft:observer":11,"minecraft:wheat_seeds":102,"minecraft:water_bucket":54,"minecraft:birch_planks":8,"minecraft:cartography_table":3,"minecraft:bubble_coral_fan":1,"minecraft:cauldron":5,"minecraft:fletching_table":8,"minecraft:cracked_stone_bricks":2,"minecraft:polished_blackstone_bricks":5,"minecraft:mossy_cobblestone":1,"minecraft:rail":107,"minecraft:light_gray_banner":3,"minecraft:tnt":5,"minecraft:crafting_table":25,"minecraft:white_bed":9,"minecraft:campfire":12,"minecraft:dark_oak_fence_gate":5,"minecraft:spruce_log":23,"minecraft:ender_eye":10,"minecraft:diamond_pickaxe":5886,"minecraft:cornflower":1,"minecraft:diamond_shovel":4201,"minecraft:wind_charge":3,"minecraft:iron_pickaxe":767,"minecraft:suspicious_stew":1,"minecraft:spruce_pressure_plate":8,"minecraft:spruce_trapdoor":19,"minecraft:spruce_sapling":12,"minecraft:pink_bed":2,"minecraft:cobblestone":523,"minecraft:potion":3,"minecraft:purple_bed":1,"minecraft:cooked_porkchop":17,"minecraft:glass_pane":24,"minecraft:candle":30,"minecraft:jukebox":2,"minecraft:cherry_sapling":6,"minecraft:moss_carpet":1,"minecraft:iron_shovel":33,"minecraft:iron_sword":240,"minecraft:stripped_jungle_wood":1,"minecraft:bell":5,"minecraft:soul_campfire":6,"minecraft:nether_bricks":19,"minecraft:carrot":562,"minecraft:tuff":5,"minecraft:obsidian":10,"minecraft:honey_bottle":2,"minecraft:glass":271,"minecraft:lantern":22,"minecraft:warped_nylium":2,"minecraft:stone_bricks":442,"minecraft:item_frame":6,"minecraft:repeater":4,"minecraft:hay_block":5,"minecraft:scaffolding":297,"minecraft:blue_shulker_box":16,"minecraft:fire_coral_fan":3,"minecraft:dark_oak_sapling":195,"minecraft:dark_oak_stairs":319,"minecraft:end_rod":3,"minecraft:stone_pickaxe":59,"minecraft:dark_oak_sign":12,"minecraft:oak_planks":15,"minecraft:ender_pearl":1,"minecraft:sugar_cane":73,"minecraft:diamond_axe":5185,"minecraft:blue_bed":2,"minecraft:white_wool":32,"minecraft:loom":6,"minecraft:crossbow":213,"minecraft:stone_brick_wall":1,"minecraft:shears":44,"minecraft:dripstone_block":6,"minecraft:redstone_torch":8,"minecraft:polished_tuff":8,"minecraft:sticky_piston":9,"minecraft:lever":6,"minecraft:firework_rocket":565,"minecraft:dark_oak_log":1157,"minecraft:bread":45,"minecraft:gravel":2,"minecraft:iron_door":6,"minecraft:golden_helmet":1,"minecraft:grindstone":10,"minecraft:andesite":3,"minecraft:chain":16,"minecraft:stripped_cherry_log":16,"minecraft:bone_meal":1026,"minecraft:purpur_block":1,"minecraft:rose_bush":3,"minecraft:flint_and_steel":294,"minecraft:redstone":7,"minecraft:spruce_planks":260,"minecraft:ender_chest":1,"minecraft:stone_hoe":59,"minecraft:oak_door":4,"minecraft:dirt":1410,"minecraft:white_carpet":45,"minecraft:hopper":23,"minecraft:spruce_stairs":85,"minecraft:cobblestone_wall":15,"minecraft:diamond_helmet":1,"minecraft:oak_wood":7,"minecraft:shulker_box":1,"minecraft:spruce_fence":8,"minecraft:granite":2,"minecraft:stone_brick_slab":162,"minecraft:dark_oak_planks":2115,"minecraft:bookshelf":10,"minecraft:oak_stairs":4,"minecraft:acacia_slab":1,"minecraft:light_gray_wool":23,"minecraft:golden_carrot":104,"minecraft:soul_soil":4,"minecraft:minecart":21,"minecraft:netherite_pickaxe":4223,"minecraft:cooked_beef":6,"minecraft:pumpkin":2,"minecraft:acacia_boat":5,"minecraft:amethyst_block":38,"minecraft:cobblestone_stairs":14,"minecraft:polished_andesite":4,"minecraft:baked_potato":134,"minecraft:birch_boat":6,"minecraft:stonecutter":8,"minecraft:cobblestone_slab":29,"minecraft:waxed_copper_block":11,"minecraft:stripped_dark_oak_log":46,"minecraft:brown_banner":4,"minecraft:dark_oak_door":20,"minecraft:smoker":4,"minecraft:flower_pot":15,"minecraft:apple":11,"minecraft:cracked_polished_blackstone_bricks":2,"minecraft:stone_slab":48,"minecraft:stone_axe":128,"minecraft:pink_petals":1,"minecraft:white_banner":1,"minecraft:bucket":55,"minecraft:pink_shulker_box":7,"minecraft:yellow_bed":2,"minecraft:smooth_stone":1},"minecraft:killed":{"minecraft:cave_spider":1,"minecraft:cod":1,"minecraft:shulker":24,"minecraft:skeleton":70,"minecraft:chicken":1,"minecraft:tropical_fish":7,"minecraft:magma_cube":22,"minecraft:salmon":44,"minecraft:pillager":2,"minecraft:zombie":138,"minecraft:cow":44,"minecraft:husk":6,"minecraft:enderman":9,"minecraft:witch":1,"minecraft:spider":31,"minecraft:silverfish":6,"minecraft:piglin_brute":3,"minecraft:piglin":1,"minecraft:zombie_villager":2,"minecraft:creeper":53,"minecraft:stray":9,"minecraft:ghast":4,"minecraft:blaze":22,"minecraft:bogged":1,"minecraft:slime":36,"minecraft:phantom":2,"minecraft:hoglin":5,"minecraft:wither_skeleton":24}},"DataVersion":3955}